{
  "domain": "cosmossdk.io",
  "docsDomain": "pkg.go.dev",
  "index": true,
  "repositories": [
    {
      "prefix": "",
      "subs": [
        "math",
        "api",
        "depinject",
        "errors",
        "core",
        "collections",
        "simapp",
        "client/v2",
        "tools/cosmovisor",
        "tools/rosetta",
        "tools/confix"
      ],
      "type": "git",
      "url": "https://github.com/cosmos/cosmos-sdk",
      "source": {
        "home": "https://github.com/cosmos/cosmos-sdk",
        "dir": "https://github.com/cosmos/cosmos-sdk/tree/main{/dir}",
        "file": "https://github.com/cosmos/cosmos-sdk/blob/main{/dir}/{file}#L{line}"
      }
    },
    {
      "prefix": "",
      "subs": [
        "confix"
      ],
      "type": "git",
      "url": "https://github.com/cosmos/cosmos-sdk",
      "source": {
        "home": "https://github.com/cosmos/cosmos-sdk",
        "dir": "https://github.com/cosmos/cosmos-sdk/tree/main/tools/{/dir}",
        "file": "https://github.com/cosmos/cosmos-sdk/blob/main/tools/{/dir}/{file}#L{line}"
      }
    }
  ]
}